odoo/addons/reorder_partner_firstname_lastname/README.rst
odoo/addons/reorder_partner_firstname_lastname/__init__.py
odoo/addons/reorder_partner_firstname_lastname/__manifest__.py
odoo/addons/reorder_partner_firstname_lastname/static/description/icon.png
odoo/addons/reorder_partner_firstname_lastname/views/res_partner.xml
odoo/addons/reorder_partner_firstname_lastname/views/res_user.xml
odoo11_addon_reorder_partner_firstname_lastname-11.0.1.0.0.dist-info/METADATA
odoo11_addon_reorder_partner_firstname_lastname-11.0.1.0.0.dist-info/WHEEL
odoo11_addon_reorder_partner_firstname_lastname-11.0.1.0.0.dist-info/top_level.txt
odoo11_addon_reorder_partner_firstname_lastname-11.0.1.0.0.dist-info/RECORD
