Metadata-Version: 2.1
Name: odoo11-addon-reorder_partner_firstname_lastname
Version: 11.0.1.0.0
Summary: Reorder firstname and lastname fields in the views.
Home-page: https://www.sygel.es
Author: Sygel
License: AGPL-3
Classifier: Programming Language :: Python
Classifier: Framework :: Odoo
Classifier: Framework :: Odoo :: 11.0
Classifier: License :: OSI Approved :: GNU Affero General Public License v3
Requires-Python: >=2.7, !=3.0.*, !=3.1.*, !=3.2.*, !=3.3.*, !=3.4.*
Requires-Dist: odoo11-addon-partner-firstname
Requires-Dist: odoo<11.1dev,>=11.0a
